styled_prose-1.0.0.dist-info/METADATA
styled_prose-1.0.0.dist-info/WHEEL
styled_prose-1.0.0.dist-info/licenses/LICENSE
styled_prose/__init__.py
styled_prose/config.py
styled_prose/creation.py
styled_prose/exceptions.py
styled_prose/fonts.py
styled_prose/py.typed
styled_prose/stylesheet.py
styled_prose/util.py
styled_prose-1.0.0.dist-info/RECORD
