Metadata-Version: 2.1
Name: styled-prose
Version: 1.0.0
Summary: Generate images and thumbnails based on bitmap transformations of rendered prose
Keywords: prose text writing pdf typography fonts art image render pillow pdf2image tgf the-glass-files
Home-page: https://styledprose.thearchitector.dev
Author-Email: thearchitector <me@eliasfgabriel.com>
License: BSD-3-Clause
Project-URL: Homepage, https://styledprose.thearchitector.dev
Project-URL: Documentation, https://styledprose.thearchitector.dev
Project-URL: Changelog, https://github.com/thearchitector/styled-prose/blob/main/CHANGELOG.md
Project-URL: Repository, https://github.com/thearchitector/styled-prose
Requires-Python: >=3.8
Requires-Dist: reportlab>=4.0.0
Requires-Dist: tomli>=2.0.0; python_version < "3.11"
Requires-Dist: pydantic>=2.0.0
Requires-Dist: httpx[http2]>=0.25.2
Requires-Dist: pdf2image>=1.16.3
Requires-Dist: Pillow>=10.1.0
